[{"Id":500344040181993500,"CreatedAt":"Fri Aug 15 18:11:29 +0000 2014","Tweet":"Destiny goes to Mars in its newest trailer - http://t.co/u38KvXkEqG","UserId":2360773571,"UserName":"BxxC Clan","UserScreenName":"bxxcclan","UserBio":"Game News & BxxC - Hungarian FPS Clan. Play like YOLO.","UserUrl":"http://t.co/lwrZJRctdl","UserFollowers":5,"UserFollowing":5,"UserAvatar":"http://pbs.twimg.com/profile_images/486280567575425026/QNC29pLt_normal.jpeg"},{"Id":500311623182352400,"CreatedAt":"Fri Aug 15 16:02:40 +0000 2014","Tweet":"New Madden ad is expensive, idiotic and unmissable - http://t.co/96OcCL7hUM","UserId":2360773571,"UserName":"BxxC Clan","UserScreenName":"bxxcclan","UserBio":"Game News & BxxC - Hungarian FPS Clan. Play like YOLO.","UserUrl":"http://t.co/lwrZJRctdl","UserFollowers":5,"UserFollowing":5,"UserAvatar":"http://pbs.twimg.com/profile_images/486280567575425026/QNC29pLt_normal.jpeg"},{"Id":500279997605875700,"CreatedAt":"Fri Aug 15 13:57:00 +0000 2014","Tweet":"Disney Infinity 2.0 comes with AI builders, game makers, interiors and more - http://t.co/GGsftcTaWl","UserId":2360773571,"UserName":"BxxC Clan","UserScreenName":"bxxcclan","UserBio":"Game News & BxxC - Hungarian FPS Clan. Play like YOLO.","UserUrl":"http://t.co/lwrZJRctdl","UserFollowers":5,"UserFollowing":5,"UserAvatar":"http://pbs.twimg.com/profile_images/486280567575425026/QNC29pLt_normal.jpeg"},{"Id":500092672640823300,"CreatedAt":"Fri Aug 15 01:32:39 +0000 2014","Tweet":"PlayStation and Xbox Twitch accounts compromised, offensive highlights posted - http://t.co/XZ0G23i8pc","UserId":2360773571,"UserName":"BxxC Clan","UserScreenName":"bxxcclan","UserBio":"Game News & BxxC - Hungarian FPS Clan. Play like YOLO.","UserUrl":"http://t.co/lwrZJRctdl","UserFollowers":5,"UserFollowing":5,"UserAvatar":"http://pbs.twimg.com/profile_images/486280567575425026/QNC29pLt_normal.jpeg"},{"Id":500062389346521100,"CreatedAt":"Thu Aug 14 23:32:18 +0000 2014","Tweet":"Pinball FX2 launches on Xbox One with Xbox 360 table import - http://t.co/GfKZSZeiSa","UserId":2360773571,"UserName":"BxxC Clan","UserScreenName":"bxxcclan","UserBio":"Game News & BxxC - Hungarian FPS Clan. Play like YOLO.","UserUrl":"http://t.co/lwrZJRctdl","UserFollowers":5,"UserFollowing":5,"UserAvatar":"http://pbs.twimg.com/profile_images/486280567575425026/QNC29pLt_normal.jpeg"},{"Id":500047322919993340,"CreatedAt":"Thu Aug 14 22:32:26 +0000 2014","Tweet":"Microsoft's Xbox TV studio reportedly in talks with Warner Bros., others to continue - http://t.co/yf73KDNEWA","UserId":2360773571,"UserName":"BxxC Clan","UserScreenName":"bxxcclan","UserBio":"Game News & BxxC - Hungarian FPS Clan. Play like YOLO.","UserUrl":"http://t.co/lwrZJRctdl","UserFollowers":5,"UserFollowing":5,"UserAvatar":"http://pbs.twimg.com/profile_images/486280567575425026/QNC29pLt_normal.jpeg"},{"Id":500025854693769200,"CreatedAt":"Thu Aug 14 21:07:08 +0000 2014","Tweet":"Now you know who to blame for all those banner ads on your Xbox One - http://t.co/6EHUjQMoT5","UserId":2360773571,"UserName":"BxxC Clan","UserScreenName":"bxxcclan","UserBio":"Game News & BxxC - Hungarian FPS Clan. Play like YOLO.","UserUrl":"http://t.co/lwrZJRctdl","UserFollowers":5,"UserFollowing":5,"UserAvatar":"http://pbs.twimg.com/profile_images/486280567575425026/QNC29pLt_normal.jpeg"},{"Id":500013462450606100,"CreatedAt":"Thu Aug 14 20:17:53 +0000 2014","Tweet":"Defense Grid 2 hits Sept. 23 - http://t.co/TCKCURtzGy","FavoriteCount":1,"UserId":2360773571,"UserName":"BxxC Clan","UserScreenName":"bxxcclan","UserBio":"Game News & BxxC - Hungarian FPS Clan. Play like YOLO.","UserUrl":"http://t.co/lwrZJRctdl","UserFollowers":5,"UserFollowing":5,"UserAvatar":"http://pbs.twimg.com/profile_images/486280567575425026/QNC29pLt_normal.jpeg"},{"Id":500006049890717700,"CreatedAt":"Thu Aug 14 19:48:26 +0000 2014","Tweet":"Remember Me creator's next game looks like Gone Home with time travel - http://t.co/anS9emOkcZ","UserId":2360773571,"UserName":"BxxC Clan","UserScreenName":"bxxcclan","UserBio":"Game News & BxxC - Hungarian FPS Clan. Play like YOLO.","UserUrl":"http://t.co/lwrZJRctdl","UserFollowers":5,"UserFollowing":5,"UserAvatar":"http://pbs.twimg.com/profile_images/486280567575425026/QNC29pLt_normal.jpeg"},{"Id":499704344380702700,"CreatedAt":"Wed Aug 13 23:49:34 +0000 2014","Tweet":"Relive the Stanley Cup Final in NHL 15 demo Aug. 26 on PS4 and Xbox One - http://t.co/lWD0BcY0pD","UserId":2360773571,"UserName":"BxxC Clan","UserScreenName":"bxxcclan","UserBio":"Game News & BxxC - Hungarian FPS Clan. Play like YOLO.","UserUrl":"http://t.co/lwrZJRctdl","UserFollowers":5,"UserFollowing":5,"UserAvatar":"http://pbs.twimg.com/profile_images/486280567575425026/QNC29pLt_normal.jpeg"}]